MANIFEST.in
PluginRemoveTriggerArea.py
README.rst
setup.cfg
setup.py
scribes.editor.remove_trigger_area.egg-info/PKG-INFO
scribes.editor.remove_trigger_area.egg-info/SOURCES.txt
scribes.editor.remove_trigger_area.egg-info/dependency_links.txt
scribes.editor.remove_trigger_area.egg-info/not-zip-safe
scribes.editor.remove_trigger_area.egg-info/requires.txt
scribes.editor.remove_trigger_area.egg-info/top_level.txt