Metadata-Version: 1.0
Name: scribes.editor.remove-trigger-area
Version: 0.2
Summary: Removes trigger area from scribes editor
Home-page: http://github.com/baverman/scribes-goodies
Author: Anton Bobrov
Author-email: bobrov@vl.ru
License: UNKNOWN
Platform: UNKNOWN
